[
    {
        "Name": "Nélson Semedo (LB)",
        "Rating": "84",
        "PS4": "109K",
        "XB1": "104K",
        "Games": "2,001,285",
        "Goals": "0.01",
        "Assists": "0.03",
        "Yellow": "0.03",
        "Red": "0",
        "Top Chem Card": "SENTINEL"
    },
    {
        "Name": "Lucas Digne (LB)",
        "Rating": "85",
        "PS4": "50K",
        "XB1": "56K",
        "Games": "1,511,929",
        "Goals": "0.01",
        "Assists": "0.04",
        "Yellow": "0.03",
        "Red": "0",
        "Top Chem Card": "ANCHOR"
    },
    {
        "Name": "Nicolás Tagliafico (LB)",
        "Rating": "84",
        "PS4": "27.75K",
        "XB1": "29.5K",
        "Games": "1,243,365",
        "Goals": "0.01",
        "Assists": "0.03",
        "Yellow": "0.03",
        "Red": "0",
        "Top Chem Card": "ANCHOR"
    },
    {
        "Name": "Roberto Carlos (LB)",
        "Rating": "86",
        "PS4": "510K",
        "XB1": "499K",
        "Games": "789,494",
        "Goals": "0.03",
        "Assists": "0.05",
        "Yellow": "0.02",
        "Red": "0",
        "Top Chem Card": "ANCHOR"
    },
    {
        "Name": "Theo Hernández (LB)",
        "Rating": "81",
        "PS4": "27.5K",
        "XB1": "22K",
        "Games": "750,163",
        "Goals": "0.02",
        "Assists": "0.03",
        "Yellow": "0.03",
        "Red": "0",
        "Top Chem Card": "SENTINEL"
    },
    {
        "Name": "Aleksandar Kolarov (LB)",
        "Rating": "84",
        "PS4": "13.5K",
        "XB1": "14.75K",
        "Games": "617,471",
        "Goals": "0.05",
        "Assists": "0.06",
        "Yellow": "0.04",
        "Red": "0",
        "Top Chem Card": "BASIC"
    },
    {
        "Name": "Marcos Alonso (LB)",
        "Rating": "84",
        "PS4": "20K",
        "XB1": "26K",
        "Games": "536,573",
        "Goals": "0.03",
        "Assists": "0.04",
        "Yellow": "0.04",
        "Red": "0.01",
        "Top Chem Card": "BASIC"
    },
    {
        "Name": "Wendell (LB)",
        "Rating": "81",
        "PS4": "15.75K",
        "XB1": "16K",
        "Games": "401,924",
        "Goals": "0.01",
        "Assists": "0.03",
        "Yellow": "0.03",
        "Red": "0",
        "Top Chem Card": "BASIC"
    },
    {
        "Name": "Andrew Robertson (LB)",
        "Rating": "86",
        "PS4": "130K",
        "XB1": "150K",
        "Games": "326,817",
        "Goals": "0.01",
        "Assists": "0.03",
        "Yellow": "0.02",
        "Red": "0",
        "Top Chem Card": "ANCHOR"
    },
    {
        "Name": "Marcos Acuña (LB)",
        "Rating": "84",
        "PS4": "32K",
        "XB1": "38K",
        "Games": "277,196",
        "Goals": "0.06",
        "Assists": "0.1",
        "Yellow": "0.02",
        "Red": "0",
        "Top Chem Card": "BASIC"
    },
    {
        "Name": "Emmanuel Petit (LB)",
        "Rating": "85",
        "PS4": "210K",
        "XB1": "236K",
        "Games": "251,444",
        "Goals": "0.04",
        "Assists": "0.09",
        "Yellow": "0.04",
        "Red": "0",
        "Top Chem Card": "SHADOW"
    },
    {
        "Name": "Paolo Maldini (LB)",
        "Rating": "88",
        "PS4": "445K",
        "XB1": "450K",
        "Games": "240,229",
        "Goals": "0.02",
        "Assists": "0.02",
        "Yellow": "0.03",
        "Red": "0",
        "Top Chem Card": "ANCHOR"
    },
    {
        "Name": "Alex Telles (LB)",
        "Rating": "86",
        "PS4": "124K",
        "XB1": "117K",
        "Games": "236,637",
        "Goals": "0.01",
        "Assists": "0.04",
        "Yellow": "0.02",
        "Red": "0",
        "Top Chem Card": "ANCHOR"
    },
    {
        "Name": "Ferland Mendy (LB)",
        "Rating": "80",
        "PS4": "13.5K",
        "XB1": "10.5K",
        "Games": "233,650",
        "Goals": "0.01",
        "Assists": "0.03",
        "Yellow": "0.02",
        "Red": "0",
        "Top Chem Card": "ANCHOR"
    },
    {
        "Name": "Gianluca Zambrotta (LB)",
        "Rating": "87",
        "PS4": "455K",
        "XB1": "460K",
        "Games": "220,359",
        "Goals": "0.02",
        "Assists": "0.04",
        "Yellow": "0.02",
        "Red": "0",
        "Top Chem Card": "SHADOW"
    },
    {
        "Name": "Javier Zanetti (LB)",
        "Rating": "87",
        "PS4": "340K",
        "XB1": "364K",
        "Games": "187,234",
        "Goals": "0.01",
        "Assists": "0.05",
        "Yellow": "0.03",
        "Red": "0",
        "Top Chem Card": "ANCHOR"
    },
    {
        "Name": "Aaron Cresswell (LB)",
        "Rating": "81",
        "PS4": "11.5K",
        "XB1": "13.75K",
        "Games": "169,573",
        "Goals": "0.01",
        "Assists": "0.04",
        "Yellow": "0.03",
        "Red": "0",
        "Top Chem Card": "BASIC"
    },
    {
        "Name": "Grimaldo (LB)",
        "Rating": "85",
        "PS4": "31K",
        "XB1": "39K",
        "Games": "167,394",
        "Goals": "0.01",
        "Assists": "0.05",
        "Yellow": "0.03",
        "Red": "0",
        "Top Chem Card": "BASIC"
    },
    {
        "Name": "Roberto Carlos (LB)",
        "Rating": "88",
        "PS4": "740K",
        "XB1": "700K",
        "Games": "150,556",
        "Goals": "0.03",
        "Assists": "0.05",
        "Yellow": "0.03",
        "Red": "0",
        "Top Chem Card": "ANCHOR"
    },
    {
        "Name": "Jordi Alba (LB)",
        "Rating": "87",
        "PS4": "59.5K",
        "XB1": "71K",
        "Games": "140,175",
        "Goals": "0.01",
        "Assists": "0.05",
        "Yellow": "0.03",
        "Red": "0",
        "Top Chem Card": "SENTINEL"
    },
    {
        "Name": "Andrew Robertson (LB)",
        "Rating": "85",
        "PS4": "25K",
        "XB1": "31.5K",
        "Games": "131,335",
        "Goals": "0.01",
        "Assists": "0.04",
        "Yellow": "0.03",
        "Red": "0",
        "Top Chem Card": "BASIC"
    },
    {
        "Name": "Marcelo (LB)",
        "Rating": "85",
        "PS4": "15.75K",
        "XB1": "14.5K",
        "Games": "116,593",
        "Goals": "0.02",
        "Assists": "0.05",
        "Yellow": "0.03",
        "Red": "0",
        "Top Chem Card": "BASIC"
    },
    {
        "Name": "Alex Sandro (LB)",
        "Rating": "85",
        "PS4": "26K",
        "XB1": "24.25K",
        "Games": "111,671",
        "Goals": "0.01",
        "Assists": "0.04",
        "Yellow": "0.03",
        "Red": "0",
        "Top Chem Card": "BASIC"
    },
    {
        "Name": "Ben Chilwell (LB)",
        "Rating": "82",
        "PS4": "12.5K",
        "XB1": "18K",
        "Games": "111,137",
        "Goals": "0.01",
        "Assists": "0.03",
        "Yellow": "0.03",
        "Red": "0",
        "Top Chem Card": "BASIC"
    },
    {
        "Name": "Jordi Alba (LB)",
        "Rating": "89",
        "PS4": "587K",
        "XB1": "597K",
        "Games": "81,418",
        "Goals": "0.01",
        "Assists": "0.05",
        "Yellow": "0.02",
        "Red": "0",
        "Top Chem Card": "ANCHOR"
    },
    {
        "Name": "Renan Augusto Lodi dos Santos (LB)",
        "Rating": "77",
        "PS4": "1K",
        "XB1": "1.2K",
        "Games": "67,780",
        "Goals": "0.01",
        "Assists": "0.03",
        "Yellow": "0.02",
        "Red": "0",
        "Top Chem Card": "BASIC"
    },
    {
        "Name": "Benjamin Mendy (LB)",
        "Rating": "80",
        "PS4": "4.8K",
        "XB1": "6.8K",
        "Games": "53,760",
        "Goals": "0.01",
        "Assists": "0.04",
        "Yellow": "0.03",
        "Red": "0",
        "Top Chem Card": "BASIC"
    },
    {
        "Name": "Nacho Monreal (LB)",
        "Rating": "82",
        "PS4": "18.5K",
        "XB1": "20.75K",
        "Games": "50,801",
        "Goals": "0.01",
        "Assists": "0.04",
        "Yellow": "0.04",
        "Red": "0",
        "Top Chem Card": "BASIC"
    },
    {
        "Name": "David Alaba (LB)",
        "Rating": "85",
        "PS4": "16.25K",
        "XB1": "21.75K",
        "Games": "50,173",
        "Goals": "0.02",
        "Assists": "0.06",
        "Yellow": "0.03",
        "Red": "0",
        "Top Chem Card": "BASIC"
    },
    {
        "Name": "Nicolás Tagliafico (LB)",
        "Rating": "86",
        "PS4": "0",
        "XB1": "0",
        "Games": "41,778",
        "Goals": "0.04",
        "Assists": "0.08",
        "Yellow": "0.01",
        "Red": "0",
        "Top Chem Card": "BASIC"
    }
]