[
    {
        "Name": "Coutinho (LW)",
        "Rating": "88",
        "PS4": "210K",
        "XB1": "195K",
        "Games": "1,590,127",
        "Goals": "0.39",
        "Assists": "0.33",
        "Yellow": "0.03",
        "Red": "0",
        "Top Chem Card": "HUNTER"
    },
    {
        "Name": "Guerreiro (LM)",
        "Rating": "85",
        "PS4": "36K",
        "XB1": "36.25K",
        "Games": "1,534,719",
        "Goals": "0.24",
        "Assists": "0.26",
        "Yellow": "0.03",
        "Red": "0",
        "Top Chem Card": "DEADEYE"
    },
    {
        "Name": "Christian Pulisic (LW)",
        "Rating": "82",
        "PS4": "21.5K",
        "XB1": "27.5K",
        "Games": "1,035,744",
        "Goals": "0.21",
        "Assists": "0.22",
        "Yellow": "0.03",
        "Red": "0",
        "Top Chem Card": "BASIC"
    },
    {
        "Name": "Bernard (LM)",
        "Rating": "84",
        "PS4": "123K",
        "XB1": "113K",
        "Games": "1,010,379",
        "Goals": "0.37",
        "Assists": "0.31",
        "Yellow": "0.02",
        "Red": "0",
        "Top Chem Card": "DEADEYE"
    },
    {
        "Name": "Antoine Griezmann (LW)",
        "Rating": "90",
        "PS4": "290K",
        "XB1": "287K",
        "Games": "832,785",
        "Goals": "0.6",
        "Assists": "0.38",
        "Yellow": "0.02",
        "Red": "0",
        "Top Chem Card": "HUNTER"
    },
    {
        "Name": "Eden Hazard (LW)",
        "Rating": "92",
        "PS4": "618K",
        "XB1": "585K",
        "Games": "653,870",
        "Goals": "0.53",
        "Assists": "0.36",
        "Yellow": "0.03",
        "Red": "0",
        "Top Chem Card": "HUNTER"
    },
    {
        "Name": "Diego Laxalt (LM)",
        "Rating": "84",
        "PS4": "27.25K",
        "XB1": "26.5K",
        "Games": "605,367",
        "Goals": "0.22",
        "Assists": "0.22",
        "Yellow": "0.03",
        "Red": "0",
        "Top Chem Card": "SNIPER"
    },
    {
        "Name": "Youcef Atal (LW)",
        "Rating": "81",
        "PS4": "16K",
        "XB1": "15.5K",
        "Games": "554,431",
        "Goals": "0.24",
        "Assists": "0.23",
        "Yellow": "0.02",
        "Red": "0",
        "Top Chem Card": "BASIC"
    },
    {
        "Name": "Kingsley Coman (LM)",
        "Rating": "87",
        "PS4": "274K",
        "XB1": "251K",
        "Games": "543,952",
        "Goals": "0.26",
        "Assists": "0.25",
        "Yellow": "0.02",
        "Red": "0",
        "Top Chem Card": "DEADEYE"
    },
    {
        "Name": "Quincy Promes (LW)",
        "Rating": "84",
        "PS4": "38.65K",
        "XB1": "40.6K",
        "Games": "490,408",
        "Goals": "0.28",
        "Assists": "0.24",
        "Yellow": "0.02",
        "Red": "0",
        "Top Chem Card": "BASIC"
    },
    {
        "Name": "David Neres (LW)",
        "Rating": "84",
        "PS4": "36.5K",
        "XB1": "35.5K",
        "Games": "469,920",
        "Goals": "0.25",
        "Assists": "0.23",
        "Yellow": "0.02",
        "Red": "0",
        "Top Chem Card": "BASIC"
    },
    {
        "Name": "Kylian Mbappé (LW)",
        "Rating": "90",
        "PS4": "855K",
        "XB1": "745K",
        "Games": "461,561",
        "Goals": "0.71",
        "Assists": "0.41",
        "Yellow": "0.02",
        "Red": "0",
        "Top Chem Card": "MARKSMAN"
    },
    {
        "Name": "Casimir Ninga (LW)",
        "Rating": "79",
        "PS4": "13.5K",
        "XB1": "15K",
        "Games": "371,088",
        "Goals": "0.32",
        "Assists": "0.24",
        "Yellow": "0.03",
        "Red": "0",
        "Top Chem Card": "BASIC"
    },
    {
        "Name": "Christian Pulisic (LM)",
        "Rating": "82",
        "PS4": "14.75K",
        "XB1": "14K",
        "Games": "364,592",
        "Goals": "0.2",
        "Assists": "0.21",
        "Yellow": "0.03",
        "Red": "0",
        "Top Chem Card": "BASIC"
    },
    {
        "Name": "Mislav Oršic (LM)",
        "Rating": "82",
        "PS4": "32.5K",
        "XB1": "33.75K",
        "Games": "344,948",
        "Goals": "0.39",
        "Assists": "0.24",
        "Yellow": "0.02",
        "Red": "0",
        "Top Chem Card": "SNIPER"
    },
    {
        "Name": "Pavel Nedvěd (LM)",
        "Rating": "86",
        "PS4": "437K",
        "XB1": "426K",
        "Games": "281,241",
        "Goals": "0.53",
        "Assists": "0.36",
        "Yellow": "0.02",
        "Red": "0",
        "Top Chem Card": "HUNTER"
    },
    {
        "Name": "Thorgan Hazard (LM)",
        "Rating": "84",
        "PS4": "19.75K",
        "XB1": "20.5K",
        "Games": "257,359",
        "Goals": "0.23",
        "Assists": "0.22",
        "Yellow": "0.02",
        "Red": "0",
        "Top Chem Card": "BASIC"
    },
    {
        "Name": "Neymar Jr (LW)",
        "Rating": "92",
        "PS4": "828K",
        "XB1": "684K",
        "Games": "238,671",
        "Goals": "0.66",
        "Assists": "0.42",
        "Yellow": "0.02",
        "Red": "0",
        "Top Chem Card": "HUNTER"
    },
    {
        "Name": "John Barnes (LW)",
        "Rating": "87",
        "PS4": "305K",
        "XB1": "334K",
        "Games": "238,039",
        "Goals": "0.53",
        "Assists": "0.34",
        "Yellow": "0.03",
        "Red": "0",
        "Top Chem Card": "HUNTER"
    },
    {
        "Name": "Pavel Nedvěd (LM)",
        "Rating": "89",
        "PS4": "670K",
        "XB1": "632K",
        "Games": "234,338",
        "Goals": "0.57",
        "Assists": "0.38",
        "Yellow": "0.03",
        "Red": "0",
        "Top Chem Card": "HUNTER"
    },
    {
        "Name": "Marc Overmars (LW)",
        "Rating": "86",
        "PS4": "176K",
        "XB1": "170K",
        "Games": "230,033",
        "Goals": "0.37",
        "Assists": "0.3",
        "Yellow": "0.02",
        "Red": "0",
        "Top Chem Card": "HUNTER"
    },
    {
        "Name": "Thierry Henry (LW)",
        "Rating": "87",
        "PS4": "500K",
        "XB1": "500K",
        "Games": "223,968",
        "Goals": "0.6",
        "Assists": "0.34",
        "Yellow": "0.02",
        "Red": "0",
        "Top Chem Card": "HUNTER"
    },
    {
        "Name": "Marc Overmars (LW)",
        "Rating": "88",
        "PS4": "433K",
        "XB1": "447K",
        "Games": "211,087",
        "Goals": "0.45",
        "Assists": "0.34",
        "Yellow": "0.02",
        "Red": "0",
        "Top Chem Card": "DEADEYE"
    },
    {
        "Name": "Alexis Sánchez (LW)",
        "Rating": "82",
        "PS4": "0",
        "XB1": "0",
        "Games": "210,369",
        "Goals": "0.2",
        "Assists": "0.19",
        "Yellow": "0.02",
        "Red": "0",
        "Top Chem Card": "BASIC"
    },
    {
        "Name": "Eden Hazard (LF)",
        "Rating": "92",
        "PS4": "350K",
        "XB1": "314K",
        "Games": "207,653",
        "Goals": "0.49",
        "Assists": "0.35",
        "Yellow": "0.02",
        "Red": "0",
        "Top Chem Card": "DEADEYE"
    },
    {
        "Name": "Hristo Stoichkov (LW)",
        "Rating": "90",
        "PS4": "715K",
        "XB1": "735K",
        "Games": "196,689",
        "Goals": "0.72",
        "Assists": "0.4",
        "Yellow": "0.03",
        "Red": "0",
        "Top Chem Card": "HUNTER"
    },
    {
        "Name": "Thierry Henry (LW)",
        "Rating": "90",
        "PS4": "895K",
        "XB1": "880K",
        "Games": "185,565",
        "Goals": "0.74",
        "Assists": "0.38",
        "Yellow": "0.03",
        "Red": "0",
        "Top Chem Card": "HUNTER"
    },
    {
        "Name": "Eden Hazard (LW)",
        "Rating": "91",
        "PS4": "260K",
        "XB1": "225K",
        "Games": "174,872",
        "Goals": "0.46",
        "Assists": "0.35",
        "Yellow": "0.02",
        "Red": "0",
        "Top Chem Card": "DEADEYE"
    },
    {
        "Name": "Robert Pirès (LM)",
        "Rating": "88",
        "PS4": "239K",
        "XB1": "252K",
        "Games": "174,797",
        "Goals": "0.35",
        "Assists": "0.28",
        "Yellow": "0.03",
        "Red": "0",
        "Top Chem Card": "HUNTER"
    },
    {
        "Name": "Francesco Caputo (LW)",
        "Rating": "81",
        "PS4": "15K",
        "XB1": "18.5K",
        "Games": "172,560",
        "Goals": "0.33",
        "Assists": "0.23",
        "Yellow": "0.03",
        "Red": "0",
        "Top Chem Card": "BASIC"
    }
]