[
    {
        "Name": "Frenkie de Jong (CM)",
        "Rating": "86",
        "PS4": "248K",
        "XB1": "200K",
        "Games": "3,388,486",
        "Goals": "0.1",
        "Assists": "0.2",
        "Yellow": "0.05",
        "Red": "0",
        "Top Chem Card": "SHADOW"
    },
    {
        "Name": "Thomas Delaney (CDM)",
        "Rating": "84",
        "PS4": "31.5K",
        "XB1": "29K",
        "Games": "3,225,078",
        "Goals": "0.1",
        "Assists": "0.16",
        "Yellow": "0.05",
        "Red": "0",
        "Top Chem Card": "ENGINE"
    },
    {
        "Name": "Georginio Wijnaldum (CM)",
        "Rating": "86",
        "PS4": "132K",
        "XB1": "122K",
        "Games": "2,126,348",
        "Goals": "0.15",
        "Assists": "0.22",
        "Yellow": "0.04",
        "Red": "0",
        "Top Chem Card": "ENGINE"
    },
    {
        "Name": "Tanguy Ndombele (CM)",
        "Rating": "81",
        "PS4": "0",
        "XB1": "0",
        "Games": "2,064,207",
        "Goals": "0.09",
        "Assists": "0.17",
        "Yellow": "0.05",
        "Red": "0",
        "Top Chem Card": "BASIC"
    },
    {
        "Name": "Kai Havertz (CAM)",
        "Rating": "86",
        "PS4": "94K",
        "XB1": "92K",
        "Games": "1,787,937",
        "Goals": "0.48",
        "Assists": "0.36",
        "Yellow": "0.04",
        "Red": "0",
        "Top Chem Card": "HUNTER"
    },
    {
        "Name": "Rodrigo (CDM)",
        "Rating": "85",
        "PS4": "21K",
        "XB1": "23.25K",
        "Games": "1,460,493",
        "Goals": "0.08",
        "Assists": "0.14",
        "Yellow": "0.06",
        "Red": "0.01",
        "Top Chem Card": "BASIC"
    },
    {
        "Name": "Frenkie de Jong (CM)",
        "Rating": "86",
        "PS4": "165K",
        "XB1": "130K",
        "Games": "1,295,609",
        "Goals": "0.1",
        "Assists": "0.2",
        "Yellow": "0.05",
        "Red": "0",
        "Top Chem Card": "ANCHOR"
    },
    {
        "Name": "Dele Alli (CAM)",
        "Rating": "87",
        "PS4": "184K",
        "XB1": "175K",
        "Games": "1,270,609",
        "Goals": "0.24",
        "Assists": "0.24",
        "Yellow": "0.04",
        "Red": "0",
        "Top Chem Card": "SHADOW"
    },
    {
        "Name": "Julian Brandt (CAM)",
        "Rating": "84",
        "PS4": "31K",
        "XB1": "28K",
        "Games": "1,226,133",
        "Goals": "0.37",
        "Assists": "0.33",
        "Yellow": "0.05",
        "Red": "0",
        "Top Chem Card": "BASIC"
    },
    {
        "Name": "Marcel Sabitzer (CAM)",
        "Rating": "85",
        "PS4": "39.5K",
        "XB1": "36.75K",
        "Games": "1,100,104",
        "Goals": "0.22",
        "Assists": "0.23",
        "Yellow": "0.04",
        "Red": "0",
        "Top Chem Card": "ENGINE"
    },
    {
        "Name": "Wilfred Ndidi (CDM)",
        "Rating": "84",
        "PS4": "39K",
        "XB1": "53.5K",
        "Games": "1,052,388",
        "Goals": "0.06",
        "Assists": "0.13",
        "Yellow": "0.05",
        "Red": "0",
        "Top Chem Card": "BASIC"
    },
    {
        "Name": "Alejandro Gómez (CAM)",
        "Rating": "86",
        "PS4": "123K",
        "XB1": "115K",
        "Games": "1,025,847",
        "Goals": "0.43",
        "Assists": "0.36",
        "Yellow": "0.03",
        "Red": "0",
        "Top Chem Card": "DEADEYE"
    },
    {
        "Name": "William Carvalho (CDM)",
        "Rating": "86",
        "PS4": "37.5K",
        "XB1": "34.75K",
        "Games": "895,169",
        "Goals": "0.12",
        "Assists": "0.16",
        "Yellow": "0.06",
        "Red": "0",
        "Top Chem Card": "ENGINE"
    },
    {
        "Name": "Dimitri Payet (CAM)",
        "Rating": "86",
        "PS4": "68K",
        "XB1": "67.5K",
        "Games": "836,736",
        "Goals": "0.38",
        "Assists": "0.34",
        "Yellow": "0.04",
        "Red": "0",
        "Top Chem Card": "MAESTRO"
    },
    {
        "Name": "Guardiola (CDM)",
        "Rating": "85",
        "PS4": "330K",
        "XB1": "300K",
        "Games": "812,814",
        "Goals": "0.04",
        "Assists": "0.14",
        "Yellow": "0.04",
        "Red": "0",
        "Top Chem Card": "ANCHOR"
    },
    {
        "Name": "James Maddison (CM)",
        "Rating": "82",
        "PS4": "12K",
        "XB1": "14.25K",
        "Games": "795,127",
        "Goals": "0.34",
        "Assists": "0.33",
        "Yellow": "0.05",
        "Red": "0",
        "Top Chem Card": "BASIC"
    },
    {
        "Name": "Ilkay Gündogan (CM)",
        "Rating": "86",
        "PS4": "27K",
        "XB1": "32K",
        "Games": "754,779",
        "Goals": "0.16",
        "Assists": "0.21",
        "Yellow": "0.05",
        "Red": "0",
        "Top Chem Card": "ENGINE"
    },
    {
        "Name": "Kevin De Bruyne (CM)",
        "Rating": "92",
        "PS4": "314K",
        "XB1": "300K",
        "Games": "729,271",
        "Goals": "0.49",
        "Assists": "0.38",
        "Yellow": "0.04",
        "Red": "0",
        "Top Chem Card": "HUNTER"
    },
    {
        "Name": "Thomas Müller (CAM)",
        "Rating": "88",
        "PS4": "181K",
        "XB1": "174K",
        "Games": "723,549",
        "Goals": "0.56",
        "Assists": "0.38",
        "Yellow": "0.03",
        "Red": "0",
        "Top Chem Card": "HUNTER"
    },
    {
        "Name": "Taison (CAM)",
        "Rating": "84",
        "PS4": "20K",
        "XB1": "23K",
        "Games": "685,213",
        "Goals": "0.44",
        "Assists": "0.34",
        "Yellow": "0.03",
        "Red": "0",
        "Top Chem Card": "DEADEYE"
    },
    {
        "Name": "Toni Kroos (CM)",
        "Rating": "90",
        "PS4": "280K",
        "XB1": "258K",
        "Games": "655,235",
        "Goals": "0.18",
        "Assists": "0.22",
        "Yellow": "0.05",
        "Red": "0",
        "Top Chem Card": "SHADOW"
    },
    {
        "Name": "Allan (CM)",
        "Rating": "87",
        "PS4": "385K",
        "XB1": "410K",
        "Games": "646,880",
        "Goals": "0.08",
        "Assists": "0.16",
        "Yellow": "0.04",
        "Red": "0",
        "Top Chem Card": "ANCHOR"
    },
    {
        "Name": "Marcelo Brozovic (CDM)",
        "Rating": "84",
        "PS4": "17.75K",
        "XB1": "18K",
        "Games": "639,276",
        "Goals": "0.11",
        "Assists": "0.16",
        "Yellow": "0.06",
        "Red": "0",
        "Top Chem Card": "BASIC"
    },
    {
        "Name": "Fabinho (CDM)",
        "Rating": "86",
        "PS4": "120K",
        "XB1": "136K",
        "Games": "616,660",
        "Goals": "0.06",
        "Assists": "0.13",
        "Yellow": "0.05",
        "Red": "0",
        "Top Chem Card": "SHADOW"
    },
    {
        "Name": "Gary Medel (CDM)",
        "Rating": "84",
        "PS4": "21.75K",
        "XB1": "22K",
        "Games": "562,019",
        "Goals": "0.12",
        "Assists": "0.15",
        "Yellow": "0.04",
        "Red": "0",
        "Top Chem Card": "BASIC"
    },
    {
        "Name": "Abdoulaye Doucouré (CM)",
        "Rating": "84",
        "PS4": "46.75K",
        "XB1": "45.25K",
        "Games": "552,009",
        "Goals": "0.09",
        "Assists": "0.17",
        "Yellow": "0.05",
        "Red": "0",
        "Top Chem Card": "ENGINE"
    },
    {
        "Name": "Steven Bergwijn (CAM)",
        "Rating": "84",
        "PS4": "15.5K",
        "XB1": "16K",
        "Games": "517,088",
        "Goals": "0.41",
        "Assists": "0.36",
        "Yellow": "0.03",
        "Red": "0",
        "Top Chem Card": "BASIC"
    },
    {
        "Name": "Miralem Pjanic (CM)",
        "Rating": "87",
        "PS4": "37.5K",
        "XB1": "38.75K",
        "Games": "509,391",
        "Goals": "0.13",
        "Assists": "0.19",
        "Yellow": "0.05",
        "Red": "0",
        "Top Chem Card": "BASIC"
    },
    {
        "Name": "Marco Verratti (CM)",
        "Rating": "87",
        "PS4": "34.75K",
        "XB1": "39.75K",
        "Games": "501,784",
        "Goals": "0.08",
        "Assists": "0.19",
        "Yellow": "0.04",
        "Red": "0",
        "Top Chem Card": "BASIC"
    },
    {
        "Name": "James Rodríguez (CAM)",
        "Rating": "88",
        "PS4": "266K",
        "XB1": "260K",
        "Games": "500,483",
        "Goals": "0.46",
        "Assists": "0.35",
        "Yellow": "0.04",
        "Red": "0",
        "Top Chem Card": "HUNTER"
    }
]