[
    {
        "Name": "Heung Min Son (CF)",
        "Rating": "87",
        "PS4": "251K",
        "XB1": "175K",
        "Games": "3,646,687",
        "Goals": "0.85",
        "Assists": "0.48",
        "Yellow": "0.03",
        "Red": "0",
        "Top Chem Card": "HUNTER"
    },
    {
        "Name": "Lucas (CF)",
        "Rating": "83",
        "PS4": "2.8K",
        "XB1": "3.1K",
        "Games": "3,475,517",
        "Goals": "0.53",
        "Assists": "0.42",
        "Yellow": "0.03",
        "Red": "0",
        "Top Chem Card": "DEADEYE"
    },
    {
        "Name": "Kylian Mbappé (ST)",
        "Rating": "89",
        "PS4": "707K",
        "XB1": "630K",
        "Games": "3,431,785",
        "Goals": "0.81",
        "Assists": "0.49",
        "Yellow": "0.02",
        "Red": "0",
        "Top Chem Card": "MARKSMAN"
    },
    {
        "Name": "Marcus Rashford (ST)",
        "Rating": "83",
        "PS4": "5.1K",
        "XB1": "5.4K",
        "Games": "3,015,920",
        "Goals": "0.74",
        "Assists": "0.48",
        "Yellow": "0.03",
        "Red": "0",
        "Top Chem Card": "BASIC"
    },
    {
        "Name": "Aubameyang (ST)",
        "Rating": "88",
        "PS4": "85K",
        "XB1": "91K",
        "Games": "2,425,354",
        "Goals": "0.87",
        "Assists": "0.51",
        "Yellow": "0.03",
        "Red": "0",
        "Top Chem Card": "SNIPER"
    },
    {
        "Name": "Alexandre Lacazette (ST)",
        "Rating": "86",
        "PS4": "16K",
        "XB1": "18K",
        "Games": "2,359,058",
        "Goals": "0.72",
        "Assists": "0.48",
        "Yellow": "0.03",
        "Red": "0",
        "Top Chem Card": "HUNTER"
    },
    {
        "Name": "Dries Mertens (CF)",
        "Rating": "87",
        "PS4": "20.5K",
        "XB1": "20K",
        "Games": "2,299,387",
        "Goals": "0.67",
        "Assists": "0.48",
        "Yellow": "0.02",
        "Red": "0",
        "Top Chem Card": "BASIC"
    },
    {
        "Name": "Timo Werner (ST)",
        "Rating": "83",
        "PS4": "2.4K",
        "XB1": "2.5K",
        "Games": "2,271,025",
        "Goals": "0.81",
        "Assists": "0.5",
        "Yellow": "0.03",
        "Red": "0",
        "Top Chem Card": "BASIC"
    },
    {
        "Name": "Antoine Griezmann (CF)",
        "Rating": "89",
        "PS4": "65K",
        "XB1": "54K",
        "Games": "2,237,245",
        "Goals": "0.68",
        "Assists": "0.47",
        "Yellow": "0.03",
        "Red": "0",
        "Top Chem Card": "HUNTER"
    },
    {
        "Name": "Sergio Agüero (ST)",
        "Rating": "89",
        "PS4": "64.5K",
        "XB1": "62K",
        "Games": "2,163,669",
        "Goals": "0.81",
        "Assists": "0.49",
        "Yellow": "0.02",
        "Red": "0",
        "Top Chem Card": "BASIC"
    },
    {
        "Name": "Lorenzo Insigne (CF)",
        "Rating": "87",
        "PS4": "21.5K",
        "XB1": "21K",
        "Games": "2,032,536",
        "Goals": "0.5",
        "Assists": "0.42",
        "Yellow": "0.02",
        "Red": "0",
        "Top Chem Card": "DEADEYE"
    },
    {
        "Name": "Roberto Firmino (CF)",
        "Rating": "86",
        "PS4": "17K",
        "XB1": "18.5K",
        "Games": "1,941,299",
        "Goals": "0.51",
        "Assists": "0.41",
        "Yellow": "0.03",
        "Red": "0",
        "Top Chem Card": "BASIC"
    },
    {
        "Name": "Cristiano Ronaldo (ST)",
        "Rating": "93",
        "PS4": "870K",
        "XB1": "765K",
        "Games": "1,927,703",
        "Goals": "1.05",
        "Assists": "0.47",
        "Yellow": "0.03",
        "Red": "0",
        "Top Chem Card": "ENGINE"
    },
    {
        "Name": "Wissam Ben Yedder (ST)",
        "Rating": "83",
        "PS4": "2.5K",
        "XB1": "2.1K",
        "Games": "1,871,630",
        "Goals": "0.73",
        "Assists": "0.46",
        "Yellow": "0.02",
        "Red": "0",
        "Top Chem Card": "BASIC"
    },
    {
        "Name": "Robert Lewandowski (ST)",
        "Rating": "89",
        "PS4": "33.75K",
        "XB1": "31K",
        "Games": "1,663,247",
        "Goals": "0.85",
        "Assists": "0.47",
        "Yellow": "0.03",
        "Red": "0",
        "Top Chem Card": "BASIC"
    },
    {
        "Name": "Luis Suárez (ST)",
        "Rating": "89",
        "PS4": "34K",
        "XB1": "31.5K",
        "Games": "1,510,289",
        "Goals": "0.78",
        "Assists": "0.48",
        "Yellow": "0.03",
        "Red": "0",
        "Top Chem Card": "BASIC"
    },
    {
        "Name": "Harry Kane (ST)",
        "Rating": "89",
        "PS4": "33.75K",
        "XB1": "32.75K",
        "Games": "1,437,190",
        "Goals": "0.83",
        "Assists": "0.46",
        "Yellow": "0.03",
        "Red": "0",
        "Top Chem Card": "BASIC"
    },
    {
        "Name": "Gabriel Jesus (ST)",
        "Rating": "82",
        "PS4": "3.9K",
        "XB1": "4.5K",
        "Games": "1,429,024",
        "Goals": "0.69",
        "Assists": "0.49",
        "Yellow": "0.03",
        "Red": "0",
        "Top Chem Card": "BASIC"
    },
    {
        "Name": "Memphis Depay (CF)",
        "Rating": "84",
        "PS4": "3.5K",
        "XB1": "3.4K",
        "Games": "1,116,292",
        "Goals": "0.64",
        "Assists": "0.42",
        "Yellow": "0.03",
        "Red": "0",
        "Top Chem Card": "BASIC"
    },
    {
        "Name": "Wilfried Zaha (CF)",
        "Rating": "83",
        "PS4": "1.7K",
        "XB1": "2K",
        "Games": "1,040,512",
        "Goals": "0.6",
        "Assists": "0.43",
        "Yellow": "0.03",
        "Red": "0",
        "Top Chem Card": "BASIC"
    },
    {
        "Name": "Rodrigo (ST)",
        "Rating": "83",
        "PS4": "1.4K",
        "XB1": "2K",
        "Games": "958,278",
        "Goals": "0.71",
        "Assists": "0.48",
        "Yellow": "0.03",
        "Red": "0",
        "Top Chem Card": "BASIC"
    },
    {
        "Name": "Iñaki Williams (ST)",
        "Rating": "82",
        "PS4": "2.5K",
        "XB1": "2.7K",
        "Games": "921,717",
        "Goals": "0.75",
        "Assists": "0.47",
        "Yellow": "0.03",
        "Red": "0",
        "Top Chem Card": "BASIC"
    },
    {
        "Name": "Morales (ST)",
        "Rating": "82",
        "PS4": "1.1K",
        "XB1": "1K",
        "Games": "885,630",
        "Goals": "0.7",
        "Assists": "0.46",
        "Yellow": "0.03",
        "Red": "0",
        "Top Chem Card": "BASIC"
    },
    {
        "Name": "Ciro Immobile (ST)",
        "Rating": "86",
        "PS4": "17.25K",
        "XB1": "17.75K",
        "Games": "793,894",
        "Goals": "0.8",
        "Assists": "0.47",
        "Yellow": "0.03",
        "Red": "0",
        "Top Chem Card": "BASIC"
    },
    {
        "Name": "Jamie Vardy (ST)",
        "Rating": "82",
        "PS4": "2K",
        "XB1": "2.2K",
        "Games": "743,493",
        "Goals": "0.77",
        "Assists": "0.49",
        "Yellow": "0.03",
        "Red": "0",
        "Top Chem Card": "BASIC"
    },
    {
        "Name": "Karim Benzema (CF)",
        "Rating": "87",
        "PS4": "21K",
        "XB1": "20K",
        "Games": "649,033",
        "Goals": "0.68",
        "Assists": "0.48",
        "Yellow": "0.03",
        "Red": "0",
        "Top Chem Card": "BASIC"
    },
    {
        "Name": "João Félix Sequeira (CF)",
        "Rating": "80",
        "PS4": "850",
        "XB1": "950",
        "Games": "449,451",
        "Goals": "0.63",
        "Assists": "0.42",
        "Yellow": "0.03",
        "Red": "0",
        "Top Chem Card": "BASIC"
    },
    {
        "Name": "Romelu Lukaku (ST)",
        "Rating": "85",
        "PS4": "9.8K",
        "XB1": "8.6K",
        "Games": "442,960",
        "Goals": "0.76",
        "Assists": "0.45",
        "Yellow": "0.03",
        "Red": "0",
        "Top Chem Card": "BASIC"
    },
    {
        "Name": "Ante Rebic (ST)",
        "Rating": "80",
        "PS4": "950",
        "XB1": "1.2K",
        "Games": "342,238",
        "Goals": "0.69",
        "Assists": "0.46",
        "Yellow": "0.03",
        "Red": "0",
        "Top Chem Card": "BASIC"
    },
    {
        "Name": "Edinson Cavani (ST)",
        "Rating": "88",
        "PS4": "26.75K",
        "XB1": "26K",
        "Games": "337,864",
        "Goals": "0.8",
        "Assists": "0.48",
        "Yellow": "0.03",
        "Red": "0",
        "Top Chem Card": "BASIC"
    }
]